SciSalt-1.6.1.dist-info/DESCRIPTION.rst
SciSalt-1.6.1.dist-info/METADATA
SciSalt-1.6.1.dist-info/RECORD
SciSalt-1.6.1.dist-info/WHEEL
SciSalt-1.6.1.dist-info/entry_points.txt
SciSalt-1.6.1.dist-info/metadata.json
SciSalt-1.6.1.dist-info/pbr.json
SciSalt-1.6.1.dist-info/top_level.txt
scisalt/__init__.py
scisalt/PWFA/__init__.py
scisalt/PWFA/ions.py
scisalt/PWFA/match.py
scisalt/PWFA/plasma.py
scisalt/accelphys/BDES2K.py
scisalt/accelphys/__init__.py
scisalt/accelphys/fitimageslice.py
scisalt/accelphys/hardcode/__init__.py
scisalt/accelphys/hardcode/setQS.py
scisalt/facettools/__init__.py
scisalt/facettools/logbookForm.py
scisalt/facettools/print2elog.py
scisalt/facettools/ui_logbookForm.py
scisalt/imageprocess/__init__.py
scisalt/imageprocess/pdf2png.py
scisalt/logging/__init__.py
scisalt/logging/mylogger.py
scisalt/matplotlib/Imshow_Slider.py
scisalt/matplotlib/Imshow_Slider_Array.py
scisalt/matplotlib/NonUniformImage.py
scisalt/matplotlib/NonUniformImage_axes.py
scisalt/matplotlib/RectangleSelector.py
scisalt/matplotlib/__init__.py
scisalt/matplotlib/addlabel.py
scisalt/matplotlib/axesfontsize.py
scisalt/matplotlib/colorbar.py
scisalt/matplotlib/figure.py
scisalt/matplotlib/hist.py
scisalt/matplotlib/hist2d.py
scisalt/matplotlib/imshow.py
scisalt/matplotlib/imshow_batch.py
scisalt/matplotlib/latexfig.py
scisalt/matplotlib/less_labels.py
scisalt/matplotlib/pcolor_axes.py
scisalt/matplotlib/plot.py
scisalt/matplotlib/plot_featured.py
scisalt/matplotlib/rgb2gray.py
scisalt/matplotlib/savefig.py
scisalt/matplotlib/setup_axes.py
scisalt/matplotlib/setup_figure.py
scisalt/matplotlib/showfig.py
scisalt/matplotlib/tile.py
scisalt/matplotlib/cmaps/__init__.py
scisalt/matplotlib/cmaps/viridis.py
scisalt/numpy/__init__.py
scisalt/numpy/frexp10.py
scisalt/numpy/functions.py
scisalt/numpy/linspaceborders.py
scisalt/numpy/linspacestep.py
scisalt/qt/ButtonMsg.py
scisalt/qt/Rectangle.py
scisalt/qt/__init__.py
scisalt/qt/get_app.py
scisalt/qt/mplwidget.py
scisalt/scipy/LinLsqFit.py
scisalt/scipy/__init__.py
scisalt/scipy/chisquare.py
scisalt/scipy/curve_fit_unscaled.py
scisalt/scipy/fft.py
scisalt/scipy/fill_missing_timestamps.py
scisalt/scipy/gaussfit.py
scisalt/utils/__init__.py
